adxbw/__init__.py
adxbw/node.py
adxbw/optimization.py
adxbw/tests/__init__.py
adxbw/tests/node_test.py
adxbw/tests/optimization_test.py
adxbw-0.1.5.dist-info/LICENSE
adxbw-0.1.5.dist-info/METADATA
adxbw-0.1.5.dist-info/WHEEL
adxbw-0.1.5.dist-info/top_level.txt
adxbw-0.1.5.dist-info/RECORD
