Metadata-Version: 2.1
Name: adxbw
Version: 0.1.5
Summary: Automated differentiation tool developed by ucxbw
Home-page: https://github.com/cs107-ucxbw/cs107-FinalProject/
Author: Lanting Li, Jiaye Chen, Jenny Dong
Author-email: lanting_li@hms.harvard.edu, jiaye_chen@hms.harvard.edu, wdong@hms.harvard.edu
License: MIT
Platform: UNKNOWN
Requires-Python: >=3.8
License-File: LICENSE
Requires-Dist: numpy
Requires-Dist: pytest
Requires-Dist: setuptools
